{
 "NotebookModel": "HP ENVY dv6 Notebook PC",
 "Author": "mbc07",
 "EcPollInterval": 1000,
 "ReadWriteWords": false,
 "CriticalTemperature": 85,
 "FanConfigurations": [
	{
	 "ReadRegister": 149,
	 "WriteRegister": 148,
	 "MinSpeedValue": 250,
	 "MaxSpeedValue": 102,
	 "IndependentReadMinMaxValues": false,
	 "MinSpeedValueRead": 0,
	 "MaxSpeedValueRead": 0,
	 "ResetRequired": false,
	 "FanSpeedResetValue": 0,
	 "FanDisplayName": "CPU/GPU fan",
	 "TemperatureThresholds": [
	  {
	   "UpThreshold": 60,
	   "DownThreshold": 0,
	   "FanSpeed": 0.0
	  },
	  {
	   "UpThreshold": 63,
	   "DownThreshold": 48,
	   "FanSpeed": 10.0
	  },
	  {
	   "UpThreshold": 66,
	   "DownThreshold": 55,
	   "FanSpeed": 20.0
	  },
	  {
	   "UpThreshold": 68,
	   "DownThreshold": 59,
	   "FanSpeed": 50.0
	  },
	  {
	   "UpThreshold": 71,
	   "DownThreshold": 63,
	   "FanSpeed": 70.0
	  },
	  {
	   "UpThreshold": 85,
	   "DownThreshold": 67,
	   "FanSpeed": 100.0
	  }
	 ],
	 "FanSpeedPercentageOverrides": []
	}
 ],
 "RegisterWriteConfigurations": [
	{
	 "WriteMode": "Set",
	 "WriteOccasion": "OnInitialization",
	 "Register": 147,
	 "Value": 20,
	 "ResetRequired": true,
	 "ResetValue": 4,
	 "ResetWriteMode": "Set",
	 "Description": "Enable manual fan speed control"
	}
 ]
}